redpoint/__init__.py
redpoint/cli.py
redpoint/grading.py
redpoint/mappings.py
redpoint/systems.py
redpoint-1.4.1.dist-info/METADATA
redpoint-1.4.1.dist-info/WHEEL
redpoint-1.4.1.dist-info/entry_points.txt
redpoint-1.4.1.dist-info/licenses/LICENSE
redpoint-1.4.1.dist-info/RECORD
