Metadata-Version: 2.4
Name: redpoint
Version: 1.4.1
Summary: Climbing grade converter
Project-URL: Homepage, https://github.com/ciszko/redpoint
Project-URL: Issues, https://github.com/ciszko/redpoint/issues
Author-email: Marcin Kalinski <marcinkalinski1997@gmail.com>
License: MIT License
License-File: LICENSE
Keywords: climbing,converter,pip
Classifier: Operating System :: OS Independent
Classifier: Programming Language :: Python :: 3
Requires-Python: >=3.8
Requires-Dist: click>=8.1.8
